{
    "swagger": "2.0",
    "info": {
        "description": "API для управления новостями и комментариями.",
        "title": "NewsFeed API",
        "termsOfService": "http://swagger.io/terms/",
        "contact": {
            "name": "API Support",
            "url": "http://www.swagger.io/support",
            "email": "support@swagger.io"
        },
        "license": {
            "name": "Apache 2.0",
            "url": "http://www.apache.org/licenses/LICENSE-2.0.html"
        },
        "version": "1.0"
    },
    "host": "localhost:8080",
    "basePath": "/",
    "paths": {
        "/auth/login": {
            "post": {
                "description": "Authenticates the user and returns a JWT token upon successful login.",
                "consumes": [
                    "application/json"
                ],
                "produces": [
                    "application/json"
                ],
                "tags": [
                    "auth"
                ],
                "summary": "Login a user",
                "parameters": [
                    {
                        "description": "User login data",
                        "name": "request",
                        "in": "body",
                        "required": true,
                        "schema": {
                            "$ref": "#/definitions/auth.LoginRequest"
                        }
                    }
                ],
                "responses": {
                    "200": {
                        "description": "token",
                        "schema": {
                            "type": "object",
                            "additionalProperties": {
                                "type": "string"
                            }
                        }
                    },
                    "400": {
                        "description": "Invalid input",
                        "schema": {
                            "type": "string"
                        }
                    },
                    "401": {
                        "description": "Invalid email or password",
                        "schema": {
                            "type": "string"
                        }
                    },
                    "500": {
                        "description": "Database error or error creating token",
                        "schema": {
                            "type": "string"
                        }
                    }
                }
            }
        },
        "/auth/register": {
            "post": {
                "description": "Creates a new user account with the provided email, username, and password.",
                "consumes": [
                    "application/json"
                ],
                "produces": [
                    "text/plain"
                ],
                "tags": [
                    "auth"
                ],
                "summary": "Register a new user",
                "parameters": [
                    {
                        "description": "User registration data",
                        "name": "request",
                        "in": "body",
                        "required": true,
                        "schema": {
                            "$ref": "#/definitions/auth.RegisterRequest"
                        }
                    }
                ],
                "responses": {
                    "201": {
                        "description": "User created successfully",
                        "schema": {
                            "type": "string"
                        }
                    },
                    "400": {
                        "description": "Invalid input",
                        "schema": {
                            "type": "string"
                        }
                    },
                    "500": {
                        "description": "Error hashing password or creating user",
                        "schema": {
                            "type": "string"
                        }
                    }
                }
            }
        },
        "/news/comments": {
            "get": {
                "description": "Get all news with their respective comment counts",
                "consumes": [
                    "application/json"
                ],
                "produces": [
                    "application/json"
                ],
                "tags": [
                    "news"
                ],
                "summary": "Get news with comments",
                "responses": {
                    "200": {
                        "description": "OK",
                        "schema": {
                            "type": "array",
                            "items": {
                                "$ref": "#/definitions/models.News"
                            }
                        }
                    },
                    "500": {
                        "description": "Internal Server Error",
                        "schema": {
                            "type": "object",
                            "additionalProperties": {
                                "type": "string"
                            }
                        }
                    }
                }
            }
        },
        "/news/{id}": {
            "get": {
                "description": "Get a single news item by its ID",
                "consumes": [
                    "application/json"
                ],
                "produces": [
                    "application/json"
                ],
                "tags": [
                    "news"
                ],
                "summary": "Get news by ID",
                "parameters": [
                    {
                        "type": "integer",
                        "description": "News ID",
                        "name": "id",
                        "in": "path",
                        "required": true
                    }
                ],
                "responses": {
                    "200": {
                        "description": "OK",
                        "schema": {
                            "$ref": "#/definitions/models.News"
                        }
                    },
                    "400": {
                        "description": "Bad Request",
                        "schema": {
                            "type": "object",
                            "additionalProperties": {
                                "type": "string"
                            }
                        }
                    },
                    "404": {
                        "description": "Not Found",
                        "schema": {
                            "type": "object",
                            "additionalProperties": {
                                "type": "string"
                            }
                        }
                    },
                    "500": {
                        "description": "Internal Server Error",
                        "schema": {
                            "type": "object",
                            "additionalProperties": {
                                "type": "string"
                            }
                        }
                    }
                }
            },
            "put": {
                "description": "Update the title, content, and image of a news article",
                "consumes": [
                    "application/json"
                ],
                "produces": [
                    "application/json"
                ],
                "tags": [
                    "news"
                ],
                "summary": "Update a news article",
                "parameters": [
                    {
                        "type": "integer",
                        "description": "News ID",
                        "name": "id",
                        "in": "path",
                        "required": true
                    },
                    {
                        "description": "Updated news data",
                        "name": "news",
                        "in": "body",
                        "required": true,
                        "schema": {
                            "$ref": "#/definitions/transport.NewsUpdateRequest"
                        }
                    }
                ],
                "responses": {
                    "200": {
                        "description": "News updated successfully",
                        "schema": {
                            "type": "string"
                        }
                    },
                    "400": {
                        "description": "Invalid request data",
                        "schema": {
                            "type": "object",
                            "additionalProperties": {
                                "type": "string"
                            }
                        }
                    },
                    "404": {
                        "description": "News not found",
                        "schema": {
                            "type": "object",
                            "additionalProperties": {
                                "type": "string"
                            }
                        }
                    },
                    "500": {
                        "description": "Internal server error",
                        "schema": {
                            "type": "object",
                            "additionalProperties": {
                                "type": "string"
                            }
                        }
                    }
                }
            },
            "delete": {
                "description": "Delete a news article by ID",
                "consumes": [
                    "application/json"
                ],
                "produces": [
                    "application/json"
                ],
                "tags": [
                    "news"
                ],
                "summary": "Delete a news article",
                "parameters": [
                    {
                        "type": "integer",
                        "description": "News ID",
                        "name": "id",
                        "in": "path",
                        "required": true
                    }
                ],
                "responses": {
                    "200": {
                        "description": "GOOD DELETE",
                        "schema": {
                            "type": "string"
                        }
                    },
                    "400": {
                        "description": "Invalid news ID",
                        "schema": {
                            "$ref": "#/definitions/models.ErrorResponse"
                        }
                    },
                    "500": {
                        "description": "Internal server error",
                        "schema": {
                            "$ref": "#/definitions/models.ErrorResponse"
                        }
                    }
                }
            }
        }
    },
    "definitions": {
        "auth.LoginRequest": {
            "type": "object",
            "properties": {
                "email": {
                    "type": "string"
                },
                "password": {
                    "type": "string"
                }
            }
        },
        "auth.RegisterRequest": {
            "type": "object",
            "properties": {
                "email": {
                    "type": "string"
                },
                "password": {
                    "type": "string"
                },
                "username": {
                    "type": "string"
                }
            }
        },
        "models.ErrorResponse": {
            "type": "object",
            "properties": {
                "error": {
                    "type": "string"
                }
            }
        },
        "models.News": {
            "type": "object",
            "properties": {
                "comments_count": {
                    "type": "integer"
                },
                "image": {
                    "type": "string"
                },
                "title": {
                    "type": "string"
                }
            }
        },
        "transport.NewsUpdateRequest": {
            "type": "object",
            "properties": {
                "content": {
                    "type": "string"
                },
                "image": {
                    "type": "string"
                },
                "title": {
                    "type": "string"
                }
            }
        }
    }
}